qorzen/__init__.py
qorzen-0.1.0.dist-info/METADATA
qorzen-0.1.0.dist-info/WHEEL
qorzen-0.1.0.dist-info/top_level.txt
qorzen-0.1.0.dist-info/RECORD
