Metadata-Version: 2.2
Name: qorzen
Version: 0.1.0
Summary: Qorzen - A modular microkernel-based platform
Home-page: https://qorzen.com
Author: Qorzen
Author-email: contact@qorzen.com
Classifier: Development Status :: 1 - Planning
Classifier: Programming Language :: Python :: 3
Classifier: License :: OSI Approved :: MIT License
Classifier: Operating System :: OS Independent
Requires-Python: >=3.12
Dynamic: author
Dynamic: author-email
Dynamic: classifier
Dynamic: description
Dynamic: description-content-type
Dynamic: home-page
Dynamic: requires-python
Dynamic: summary
